[
  {
    "py/object": "model.group.Group",
    "name": "",
    "header": "",
    "footer": "",
    "id": null
  },
  {
    "py/object": "model.group.Group",
    "name": "nameeB|TyX/",
    "header": "header{\\u8 }",
    "footer": "footer#2aen=S$B2T.",
    "id": null
  },
  {
    "py/object": "model.group.Group",
    "name": "nameS\\M ",
    "header": "header7",
    "footer": "footerkr!'(1KQ2  ",
    "id": null
  },
  {
    "py/object": "model.group.Group",
    "name": "name[",
    "header": "header1qkRZAO(S e%",
    "footer": "footer})Pg,= Fh",
    "id": null
  },
  {
    "py/object": "model.group.Group",
    "name": "name",
    "header": "header(,tcR2\"% !EWV",
    "footer": "footerAu-/~8g~EK8M",
    "id": null
  },
  {
    "py/object": "model.group.Group",
    "name": "name6n",
    "header": "header *ZKH",
    "footer": "footer;]2c@",
    "id": null
  }
]